julep/__init__.py
julep/_base_client.py
julep/_client.py
julep/_compat.py
julep/_constants.py
julep/_exceptions.py
julep/_files.py
julep/_models.py
julep/_qs.py
julep/_resource.py
julep/_response.py
julep/_streaming.py
julep/_types.py
julep/_version.py
julep/_wrappers.py
julep/pagination.py
julep/py.typed
julep/_utils/__init__.py
julep/_utils/_compat.py
julep/_utils/_datetime_parse.py
julep/_utils/_logs.py
julep/_utils/_proxy.py
julep/_utils/_reflection.py
julep/_utils/_resources_proxy.py
julep/_utils/_streams.py
julep/_utils/_sync.py
julep/_utils/_transform.py
julep/_utils/_typing.py
julep/_utils/_utils.py
julep/lib/.keep
julep/lib/__init__.py
julep/resources/__init__.py
julep/resources/docs.py
julep/resources/files.py
julep/resources/healthz.py
julep/resources/jobs.py
julep/resources/projects.py
julep/resources/secrets.py
julep/resources/sessions.py
julep/resources/tasks.py
julep/resources/agents/__init__.py
julep/resources/agents/agents.py
julep/resources/agents/docs.py
julep/resources/agents/tools.py
julep/resources/executions/__init__.py
julep/resources/executions/executions.py
julep/resources/executions/status.py
julep/resources/executions/transitions.py
julep/resources/users/__init__.py
julep/resources/users/docs.py
julep/resources/users/users.py
julep/types/__init__.py
julep/types/agent.py
julep/types/agent_create_or_update_params.py
julep/types/agent_create_params.py
julep/types/agent_delete_response.py
julep/types/agent_list_models_response.py
julep/types/agent_list_params.py
julep/types/agent_reset_params.py
julep/types/agent_update_params.py
julep/types/base_token_log_prob.py
julep/types/case_then_output.py
julep/types/chat_response.py
julep/types/chosen_bash20241022.py
julep/types/chosen_bash20241022_param.py
julep/types/chosen_computer20241022.py
julep/types/chosen_computer20241022_param.py
julep/types/chosen_function_call.py
julep/types/chosen_function_call_param.py
julep/types/chosen_text_editor20241022.py
julep-2.21.0.dist-info/METADATA
julep-2.21.0.dist-info/WHEEL
julep-2.21.0.dist-info/licenses/LICENSE
julep-2.21.0.dist-info/RECORD
